AUTHORS.rst
LICENSE.vyoma
MANIFEST.in
README.rst
pyproject.toml
setup.cfg
setup.py
reporg/__init__.py
reporg/constants.py
reporg/log.py
reporg/main.py
reporg/org.py
reporg/requirements.txt
reporg/utils.py
reporg.egg-info/PKG-INFO
reporg.egg-info/SOURCES.txt
reporg.egg-info/dependency_links.txt
reporg.egg-info/entry_points.txt
reporg.egg-info/not-zip-safe
reporg.egg-info/requires.txt
reporg.egg-info/top_level.txt
tests/__init__.py
tests/test_reporg.py