Metadata-Version: 2.1
Name: reporg
Version: 1.0.3
Summary: Repo organizer
Home-page: https://gitlab.com/riscv_verification/reporg
Author: vsys
Author-email: vsys2021@gmail.com
License: MIT license
Keywords: reporg
Platform: UNKNOWN
Classifier: Programming Language :: Python :: 3.8
Classifier: License :: OSI Approved :: BSD License
Classifier: Development Status :: 4 - Beta
Requires-Python: >=3.8.5
License-File: LICENSE.vyoma
License-File: AUTHORS.rst
